<?xml version="1.0" encoding="utf-8"?>
<open-rechtspraak>
  <rdf:RDF xmlns:rdf="http://www.w3.org/1999/02/22-rdf-syntax-ns#" xmlns:ecli="https://e-justice.europa.eu/ecli" xmlns:tr="http://tuchtrecht.overheid.nl/" xmlns:eu="http://publications.europa.eu/celex/" xmlns:dcterms="http://purl.org/dc/terms/" xmlns:bwb="bwb-dl" xmlns:cvdr="http://decentrale.regelgeving.overheid.nl/cvdr/" xmlns:psi="http://psi.rechtspraak.nl/" xmlns:rdfs="http://www.w3.org/2000/01/rdf-schema#">
    <rdf:Description>
      <dcterms:identifier>ECLI:NL:RBNHO:2020:3364</dcterms:identifier>
      <dcterms:format>text/xml</dcterms:format>
      <dcterms:accessRights>public</dcterms:accessRights>
      <dcterms:modified>2020-05-08T15:00:30</dcterms:modified>
      <dcterms:issued rdfs:label="Publicatiedatum">2020-05-04</dcterms:issued>
      <dcterms:publisher resourceIdentifier="http://rechtspraak.nl/">Raad voor de Rechtspraak</dcterms:publisher>
      <dcterms:language>nl</dcterms:language>
      <dcterms:creator rdfs:label="Instantie" resourceIdentifier="http://standaarden.overheid.nl/owms/terms/Rechtbank_Noord-Holland" scheme="overheid.RechterlijkeMacht">Rechtbank Noord-Holland</dcterms:creator>
      <dcterms:date rdfs:label="Uitspraakdatum">2020-05-06</dcterms:date>
      <psi:zaaknummer rdfs:label="Zaaknr">HAA 20_2082</psi:zaaknummer>
      <dcterms:type rdf:language="nl" resourceIdentifier="http://psi.rechtspraak.nl/uitspraak">Uitspraak</dcterms:type>
      <psi:procedure rdf:language="nl" rdfs:label="Procedure" resourceIdentifier="http://psi.rechtspraak.nl/procedure#voorlopigeVoorziening">Voorlopige voorziening</psi:procedure>
      <dcterms:coverage>NL</dcterms:coverage>
      <dcterms:spatial rdfs:label="Zittingsplaats">Haarlem</dcterms:spatial>
      <dcterms:subject rdfs:label="Rechtsgebied" resourceIdentifier="http://psi.rechtspraak.nl/rechtsgebied#bestuursrecht">Bestuursrecht</dcterms:subject>
      <dcterms:hasVersion rdfs:label="Vindplaatsen" resourceIdentifier="http://psi.rechtspraak.nl/vindplaats">
        <rdf:list>
          <rdf:li>Rechtspraak.nl</rdf:li>
        </rdf:list>
      </dcterms:hasVersion>
    </rdf:Description>
    <rdf:Description rdf:about="http://deeplink.rechtspraak.nl/uitspraak?id=ECLI:NL:RBNHO:2020:3364">
      <dcterms:identifier>http://deeplink.rechtspraak.nl/uitspraak?id=ECLI:NL:RBNHO:2020:3364</dcterms:identifier>
      <dcterms:format>text/html</dcterms:format>
      <dcterms:accessRights>public</dcterms:accessRights>
      <dcterms:modified>2020-05-08T09:41:55</dcterms:modified>
      <dcterms:issued rdfs:label="Publicatiedatum">2020-05-08</dcterms:issued>
      <dcterms:publisher resourceIdentifier="http://rechtspraak.nl/">Raad voor de Rechtspraak</dcterms:publisher>
      <dcterms:language>nl</dcterms:language>
      <dcterms:title rdf:language="nl">ECLI:NL:RBNHO:2020:3364 Rechtbank Noord-Holland , 06-05-2020 / HAA 20_2082</dcterms:title>
      <dcterms:abstract resourceIdentifier="../../rs:inhoudsindicatie" />
    </rdf:Description>
  </rdf:RDF>
  <inhoudsindicatie id="ECLI:NL:RBNHO:2020:3364:INH" lang="nl" xml:space="preserve" xmlns="http://www.rechtspraak.nl/schema/rechtspraak-1.0" xmlns:xsi="http://www.w3.org/2001/XMLSchema-instance" xmlns:xsd="http://www.w3.org/2001/XMLSchema">
      <para>Voorlopige voorziening. Voorzieningen verstrekt in de vorm van persoonsgebonden budgetten. Geschil ziet op hoogte van een deel van de toegekende budgetten. Geen sprake van zodanig spoedeisend belang dat verzoekster de bezwaarprocedure niet kan afwachten. De voorzieningenrechter wijst het verzoek om voorlopige voorziening af.</para>
    </inhoudsindicatie>
  <uitspraak id="ECLI:NL:RBNHO:2020:3364:DOC" lang="nl" xml:space="preserve" xmlns="http://www.rechtspraak.nl/schema/rechtspraak-1.0" xmlns:xsi="http://www.w3.org/2001/XMLSchema-instance" xmlns:xsd="http://www.w3.org/2001/XMLSchema" xmlns:xlink="http://www.w3.org/1999/xlink">
  <uitspraak.info>
    <para />
    <bridgehead role="bold">RECHTBANK NOORD-HOLLAND</bridgehead>
    <para />
    <parablock>
      <para>Zittingsplaats Haarlem</para>
    </parablock>
    <para />
    <parablock>
      <para>Bestuursrecht</para>
    </parablock>
    <para />
    <parablock>
      <para>zaaknummer: HAA 20/2082</para>
    </parablock>
    <para />
    <bridgehead role="bold">uitspraak van de voorzieningenrechter van 6 mei 2020 in de zaak tussen </bridgehead>
    <para />
    <bridgehead role="bold">
      [naam], te [woonplaats], verzoekster</bridgehead>
    <para>gemachtigde: mr. M. Helmantel, advocaat te Sappemeer, </para>
    <para />
    <parablock>
      <para>en </para>
    </parablock>
    <para />
    <parablock>
      <para>
        <emphasis role="bold">het college van burgemeester en wethouders van de gemeente Zandvoort</emphasis>, verweerder.</para>
    </parablock>
    <para />
    <para />
  </uitspraak.info>
  <section role="procesverloop">
    <title>Procesverloop</title>
    <para />
    <parablock>
      <para>Bij (tweede herstel) besluit van 24 december 2019 (het primaire besluit) heeft verweerder het eerder aan verzoekster verleende persoonsgebonden budget (pgb) deels gewijzigd wat betreft de hoogte van de toegekende uurbedragen en het pgv verstrekt voor:</para>
    </parablock>
    <itemizedlist mark="-">
      <listitem>
        <para>begeleiding ambulant middelzware ondersteuning voor onbepaalde tijd vanaf 1 februari 2020, met een budget van € 44,20 per uur en met een omvang van 120 minuten per week;</para>
      </listitem>
      <listitem>
        <para>begeleiding individueel (informele zorg) behalen van doelen voor de periode 1 februari 2020 tot en met 31 juli 2020, met een budget van € 32,10 per uur en met een omvang van 120 minuten per week;</para>
      </listitem>
      <listitem>
        <para>begeleiding individueel (informele zorg) behalen van doelen voor onbepaalde tijd vanaf 1 augustus 2020, met een budget van € 20,- per uur en met een omvang van 120 minuten per week;</para>
      </listitem>
      <listitem>
        <para>begeleiding individueel (informele zorg) bij vervoer voor de periode 1 februari 2020 tot en met 31 juli 2020, met een budget van € 32,10 per uur en met een omvang van 150 minuten per week;</para>
      </listitem>
      <listitem>
        <para>begeleiding individueel (informele zorg) behalend van doelen voor onbepaalde tijd vanaf 1 augustus 2020, met een budget van € 20,- per uur en met een omvang van 150 minuten per week.</para>
      </listitem>
    </itemizedlist>
    <para />
    <parablock>
      <para>Verzoekster heeft tegen het primaire besluit bezwaar gemaakt. Zij heeft de voorzieningenrechter verzocht om een voorlopige voorziening te treffen.</para>
    </parablock>
    <para />
  </section>
  <section>
    <title>Overwegingen</title>
    <para />
    <orderedlist numeration="arabic">
      <listitem>
        <para>De voorzieningenrechter doet op grond van artikel 8:83, derde lid, van de Algemene wet bestuursrecht (Awb) uitspraak zonder zitting. <?linebreak?></para>
      </listitem>
      <listitem>
        <para>De voorzieningenrechter treft op grond van artikel 8:81, eerste lid, van de Awb alleen een voorlopige voorziening als “onverwijlde spoed” dat vereist. Bij het bestreden besluit zijn aan verzoekster voorzieningen verstrekt in de vorm van persoonsgebonden budgetten. Het geschil tussen partijen ziet op de hoogte van een deel van de toegekende budgetten, waarbij sprake is van verlaging van het uurtarief voor een deel van de begeleiding met een gewenningsperiode. Verweerder heeft voor een van de twee begeleiders het zogenaamde formele tarief gewijzigd in het informele tarief. Bij een dergelijk financieel geschil is van een spoedeisend belang niet snel sprake. In beginsel kan namelijk na afloop van de bodemzaak het bedrag waarover het geschil gaat, indien verzoekster in de hoofdzaak gelijk krijgt, alsnog worden betaald, zo nodig met vergoeding van de wettelijke rente. Weliswaar heeft verzoekster aangegeven dat de zorgverleners als gevolg van het bestreden besluit dreigen af te haken. Nog daargelaten dat dat alleen op een van de twee dienstverleners betrekking kan hebben, is evenwel niet gebleken dat dit zich al heeft geëffectueerd en verzoekster op dit moment is verstoken van begeleiding. Daarom is geen sprake van een zodanig spoedeisend belang dat verzoekster de bezwaarprocedure niet kan afwachten. Daarbij is ook van belang dat nu het bezwaar tegen het bestreden besluit dateert van 16 januari 2020, de beslissing op bezwaar binnen afzienbare tijd is te verwachten.</para>
      </listitem>
    </orderedlist>
    <para />
    <para>3. Gelet op hetgeen hiervoor is overwogen, wijst de voorzieningenrechter het verzoek om een voorlopige voorziening af.</para>
    <para />
    <para>4. Voor een proceskostenveroordeling bestaat geen aanleiding.</para>
    <para />
  </section>
  <section role="beslissing">
    <title>Beslissing</title>
    <para />
    <parablock>
      <para>De voorzieningenrechter wijst het verzoek om voorlopige voorziening af.</para>
    </parablock>
    <para />
    <para />
    <parablock>
      <para>Deze uitspraak is gedaan door mr. R.H.M. Bruin, voorzieningenrechter, in aanwezigheid van mr. P.C. van der Vlugt, griffier<emphasis role="italic">.</emphasis></para>
    </parablock>
    <para />
    <parablock>
      <para>Deze uitspraak is gedaan op 6 mei 2020. Als gevolg van maatregelen rondom het coronavirus is deze uitspraak niet uitgesproken op een openbare uitsprakenzitting. Zodra het openbaar uitspreken weer mogelijk is, wordt deze uitspraak, voor zover nodig, alsnog in het openbaar uitgesproken. </para>
    </parablock>
    <para />
    <para />
    <para />
    <para />
    <para />
    <para />
    <parablock>
      <para>griffier	voorzieningenrechter</para>
    </parablock>
    <para />
    <para />
    <parablock>
      <para>Een afschrift van deze uitspraak is verzonden aan partijen op:</para>
    </parablock>
    <para />
    <para />
  </section>
  <section>
    <title>Rechtsmiddel</title>
    <para>Tegen deze uitspraak staat geen rechtsmiddel open.</para>
    <para />
    <para />
  </section>
</uitspraak>
</open-rechtspraak>